siru/__about__.py
siru/__init__.py
siru/ate.py
siru/dut.py
siru/gpio.py
siru/preat.py
siru/tasks.py
siru-0.7.dist-info/METADATA
siru-0.7.dist-info/WHEEL
siru-0.7.dist-info/licenses/LICENSE.txt
siru-0.7.dist-info/RECORD
