Metadata-Version: 2.1
Name: siru
Version: 0.7
Summary: Automated tests on hardware for embedded systems
Project-URL: Documentation, https://github.com/labmicro/siru#readme
Project-URL: Issues, https://github.com/labmicro/siru/issues
Project-URL: Source, https://github.com/labmicro/siru
Author-email: Esteban Volentini <evolentini@herrera.unt.edu.ar>
License-Expression: MIT
License-File: LICENSE.txt
Keywords: automated testing,embedded systems
Classifier: Development Status :: 2 - Pre-Alpha
Classifier: Environment :: Console
Classifier: Framework :: Robot Framework
Classifier: Intended Audience :: Developers
Classifier: License :: OSI Approved :: MIT License
Classifier: Operating System :: MacOS :: MacOS X
Classifier: Operating System :: POSIX
Classifier: Operating System :: Unix
Classifier: Programming Language :: C
Classifier: Programming Language :: Python :: 3 :: Only
Classifier: Topic :: Software Development :: Testing :: Acceptance
Requires-Python: >=3.7
Requires-Dist: crc~=4.1
Requires-Dist: mako~=1.2
Requires-Dist: pyserial~=3.5
Requires-Dist: pyyaml-include~=1.3
Requires-Dist: pyyaml~=6.0
